flask_httpauth-stubs/__init__.pyi
Flask_HTTPAuth_stubs-0.1.6.dist-info/LICENSE
Flask_HTTPAuth_stubs-0.1.6.dist-info/METADATA
Flask_HTTPAuth_stubs-0.1.6.dist-info/WHEEL
Flask_HTTPAuth_stubs-0.1.6.dist-info/top_level.txt
Flask_HTTPAuth_stubs-0.1.6.dist-info/RECORD
