Metadata-Version: 2.1
Name: Flask-HTTPAuth-stubs
Version: 0.1.6
Summary: Mypy plugin and stubs for Flask-HTTPAuth
Home-page: 
Download-URL: 
Author: Martin Thoma
Author-email: info@martin-thoma.de
Maintainer: Martin Thoma
Maintainer-email: info@martin-thoma.de
License: MIT license
Keywords: utility,mypy,stubs
Classifier: Development Status :: 4 - Beta
Classifier: Intended Audience :: Developers
Classifier: Natural Language :: English
Classifier: Framework :: Flask
License-File: LICENSE
Requires-Dist: mypy >=0.720
Requires-Dist: typing-extensions >=3.7.4
Requires-Dist: Flask-HTTPAuth >=4.0.0
